MANIFEST.in
README.md
setup.py
picontrol/PN532.py
picontrol/__init__.py
picontrol/button_classic.py
picontrol/button_pi.py
picontrol/config.py
picontrol/control.py
picontrol/fan.py
picontrol/gameend.py
picontrol/gamestart.py
picontrol/ndef.py
picontrol/nfc.py
picontrol/processes.py
picontrol.egg-info/PKG-INFO
picontrol.egg-info/SOURCES.txt
picontrol.egg-info/dependency_links.txt
picontrol.egg-info/entry_points.txt
picontrol.egg-info/requires.txt
picontrol.egg-info/top_level.txt
picontrol/webserver/__init__.py
picontrol/webserver/game.py
picontrol/webserver/nfc.py
picontrol/webserver/profile.py
picontrol/webserver/server.py
picontrol/webserver/settings.py
picontrol/webserver/user.py
picontrol/webserver/static/assets/app/app.js
picontrol/webserver/static/assets/app/app.service.js
picontrol/webserver/static/assets/app/alerts/alerts.controller.js
picontrol/webserver/static/assets/app/alerts/alerts.service.js
picontrol/webserver/static/assets/app/alerts/alerts_modal.html
picontrol/webserver/static/assets/app/auth/auth.service.js
picontrol/webserver/static/assets/app/auth/auth_interceptor.service.js
picontrol/webserver/static/assets/app/dashboard/dashboard.controller.js
picontrol/webserver/static/assets/app/dashboard/dashboard.html
picontrol/webserver/static/assets/app/dashboard/dashboard.route.js
picontrol/webserver/static/assets/app/dashboard/dashboard.service.js
picontrol/webserver/static/assets/app/games/games.controller.js
picontrol/webserver/static/assets/app/games/games.html
picontrol/webserver/static/assets/app/games/games.route.js
picontrol/webserver/static/assets/app/games/games.service.js
picontrol/webserver/static/assets/app/games/modal/addGame.controller.js
picontrol/webserver/static/assets/app/games/modal/addGame.html
picontrol/webserver/static/assets/app/games/modal/game.controller.js
picontrol/webserver/static/assets/app/games/modal/game.html
picontrol/webserver/static/assets/app/login/login.controller.js
picontrol/webserver/static/assets/app/login/login.html
picontrol/webserver/static/assets/app/login/login.route.js
picontrol/webserver/static/assets/app/main/main.controller.js
picontrol/webserver/static/assets/app/main/main.html
