Metadata-Version: 1.0
Name: picontrol
Version: 1.1
Summary: A RaspberryPi/RetroPi controller/webserver for game, nfc, and power control
Home-page: https://github.com/Lemmons/picontrol
Author: Scott Lemmon
Author-email: skot.biz@gmail.com
License: UNKNOWN
Platform: UNKNOWN
